backports/__init__.py
backports/cached_property/__init__.py
backports/cached_property/__init__.pyi
backports/cached_property/_version.py
backports/cached_property/py.typed
backports.cached_property-1.0.2.dist-info/LICENSE
backports.cached_property-1.0.2.dist-info/METADATA
backports.cached_property-1.0.2.dist-info/WHEEL
backports.cached_property-1.0.2.dist-info/top_level.txt
backports.cached_property-1.0.2.dist-info/zip-safe
backports.cached_property-1.0.2.dist-info/RECORD
