Metadata-Version: 2.1
Name: backports.cached-property
Version: 1.0.2
Summary: cached_property() - computed once per instance, cached as attribute
Home-page: https://github.com/penguinolog/backports.cached_property
Author: Aleksei Stepanov
Author-email: penguinolog@gmail.com
Maintainer: Aleksei Stepanov penguinolog@gmail.com
License: MIT License
Project-URL: Bug Tracker, https://github.com/penguinolog/backports.cached_property/issues
Keywords: caching,development
Classifier: Development Status :: 5 - Production/Stable
Classifier: Intended Audience :: Developers
Classifier: Topic :: Software Development :: Libraries :: Python Modules
Classifier: License :: OSI Approved :: MIT License
Classifier: Programming Language :: Python :: 3
Classifier: Programming Language :: Python :: 3.6
Classifier: Programming Language :: Python :: 3.7
Classifier: Programming Language :: Python :: 3.8
Classifier: Programming Language :: Python :: 3.9
Classifier: Programming Language :: Python :: Implementation :: CPython
Classifier: Programming Language :: Python :: Implementation :: PyPy
Requires-Python: >=3.6.0
License-File: LICENSE
